prefect_datahub/__init__.py
prefect_datahub/datahub_emitter.py
prefect_datahub/entities.py
prefect_datahub/example/__init__.py
prefect_datahub/example/flow.py
prefect_datahub/example/save_block.py
prefect_datahub-15.0.4.dist-info/METADATA
prefect_datahub-15.0.4.dist-info/WHEEL
prefect_datahub-15.0.4.dist-info/entry_points.txt
prefect_datahub-15.0.4.dist-info/top_level.txt
prefect_datahub-15.0.4.dist-info/RECORD
