Metadata-Version: 2.2
Name: prefect-datahub
Version: 15.0.4
Summary: Datahub prefect block to capture executions and send to Datahub
Home-page: https://datahubproject.io/
License: Apache License 2.0
Project-URL: Documentation, https://datahubproject.io/docs/
Project-URL: Source, https://github.com/datahub-project/datahub
Project-URL: Changelog, https://github.com/datahub-project/datahub/releases
Classifier: Development Status :: 5 - Production/Stable
Classifier: Programming Language :: Python
Classifier: Programming Language :: Python :: 3
Classifier: Programming Language :: Python :: 3 :: Only
Classifier: Intended Audience :: Developers
Classifier: Intended Audience :: Information Technology
Classifier: Intended Audience :: System Administrators
Classifier: License :: OSI Approved
Classifier: License :: OSI Approved :: Apache Software License
Classifier: Operating System :: Unix
Classifier: Operating System :: POSIX :: Linux
Classifier: Environment :: Console
Classifier: Environment :: MacOS X
Classifier: Topic :: Software Development
Requires-Python: >=3.8
Requires-Dist: requests
Requires-Dist: importlib-metadata<5.0.0,>=4.4.0; python_version < "3.8"
Requires-Dist: acryl-datahub[datahub-rest]
Requires-Dist: requests_file
Requires-Dist: prefect<3.0.0,>=2.0.0
Provides-Extra: dev
Requires-Dist: types-PyYAML; extra == "dev"
Requires-Dist: sqlalchemy-stubs; extra == "dev"
Requires-Dist: types-python-dateutil; extra == "dev"
Requires-Dist: mypy>=1.4.0; extra == "dev"
Requires-Dist: importlib-metadata<5.0.0,>=4.4.0; python_version < "3.8" and extra == "dev"
Requires-Dist: types-tabulate; extra == "dev"
Requires-Dist: pytest>=6.2.2; extra == "dev"
Requires-Dist: pytest-asyncio>=0.16.0; extra == "dev"
Requires-Dist: types-setuptools; extra == "dev"
Requires-Dist: tox; extra == "dev"
Requires-Dist: pydantic>=1.10; extra == "dev"
Requires-Dist: types-cachetools; extra == "dev"
Requires-Dist: types-pytz; extra == "dev"
Requires-Dist: build; extra == "dev"
Requires-Dist: requests-mock; extra == "dev"
Requires-Dist: types-requests; extra == "dev"
Requires-Dist: types-click==0.1.12; extra == "dev"
Requires-Dist: requests; extra == "dev"
Requires-Dist: types-toml; extra == "dev"
Requires-Dist: types-freezegun; extra == "dev"
Requires-Dist: freezegun; extra == "dev"
Requires-Dist: coverage>=5.1; extra == "dev"
Requires-Dist: pytest-cov>=2.8.1; extra == "dev"
Requires-Dist: acryl-datahub[datahub-rest]; extra == "dev"
Requires-Dist: ruff==0.9.2; extra == "dev"
Requires-Dist: twine; extra == "dev"
Requires-Dist: deepdiff; extra == "dev"
Requires-Dist: requests_file; extra == "dev"
Requires-Dist: prefect<3.0.0,>=2.0.0; extra == "dev"
Requires-Dist: types-six; extra == "dev"
Requires-Dist: packaging; extra == "dev"
Requires-Dist: jsonpickle; extra == "dev"
Requires-Dist: types-dataclasses; extra == "dev"
Dynamic: classifier
Dynamic: description
Dynamic: description-content-type
Dynamic: home-page
Dynamic: license
Dynamic: project-url
Dynamic: provides-extra
Dynamic: requires-dist
Dynamic: requires-python
Dynamic: summary
